signxml/__init__.py
signxml/algorithms.py
signxml/exceptions.py
signxml/processor.py
signxml/py.typed
signxml/signer.py
signxml/verifier.py
signxml/__pyinstaller/__init__.py
signxml/__pyinstaller/hook-signxml.py
signxml/schemas/__init__.py
signxml/schemas/xmldsig-core-schema.xsd
signxml/schemas/xmldsig1-schema.xsd
signxml/schemas/xmldsig11-schema.xsd
signxml/util/__init__.py
signxml/xades/__init__.py
signxml/xades/xades.py
signxml/xades/schemas/XAdES.xsd
signxml/xades/schemas/XAdES01903v132-201506.xsd
signxml/xades/schemas/XAdES01903v132-201601.xsd
signxml/xades/schemas/XAdES01903v141-201506.xsd
signxml/xades/schemas/XAdES01903v141-201601.xsd
signxml/xades/schemas/XAdESv141.xsd
signxml/xades/schemas/__init__.py
signxml-4.2.2.dist-info/METADATA
signxml-4.2.2.dist-info/WHEEL
signxml-4.2.2.dist-info/licenses/LICENSE
signxml-4.2.2.dist-info/licenses/NOTICE
signxml-4.2.2.dist-info/RECORD
