Metadata-Version: 2.4
Name: signxml
Version: 4.2.2
Summary: Python XML Signature and XAdES library
Project-URL: Homepage, https://github.com/XML-Security/signxml
Project-URL: Documentation, https://xml-security.github.io/signxml/
Project-URL: Source Code, https://github.com/XML-Security/signxml
Project-URL: Issue Tracker, https://github.com/XML-Security/signxml/issues
Project-URL: Change Log, https://github.com/XML-Security/signxml/blob/main/Changes.rst
Author: Andrey Kislyuk
Author-email: kislyuk@gmail.com
Maintainer: Andrey Kislyuk
Maintainer-email: kislyuk@gmail.com
License: Apache Software License
License-File: LICENSE
License-File: NOTICE
Classifier: Development Status :: 5 - Production/Stable
Classifier: Intended Audience :: Developers
Classifier: License :: OSI Approved :: Apache Software License
Classifier: Operating System :: MacOS :: MacOS X
Classifier: Operating System :: POSIX
Classifier: Programming Language :: Python
Classifier: Programming Language :: Python :: 3
Classifier: Programming Language :: Python :: 3.8
Classifier: Programming Language :: Python :: 3.9
Classifier: Programming Language :: Python :: 3.10
Classifier: Programming Language :: Python :: 3.11
Classifier: Programming Language :: Python :: 3.12
Classifier: Programming Language :: Python :: 3.13
Classifier: Programming Language :: Python :: Implementation :: CPython
Classifier: Programming Language :: Python :: Implementation :: PyPy
Classifier: Topic :: Software Development
Classifier: Topic :: Software Development :: Libraries :: Python Modules
Requires-Python: >=3.8
Requires-Dist: certifi>=2023.11.17
Requires-Dist: cryptography>=43
Requires-Dist: lxml<7,>=5.2.1
Provides-Extra: test
Requires-Dist: build; extra == 'test'
Requires-Dist: coverage; extra == 'test'
Requires-Dist: lxml-stubs; extra == 'test'
Requires-Dist: mypy; extra == 'test'
Requires-Dist: ruff; extra == 'test'
Requires-Dist: wheel; extra == 'test'
